setup.py
distributions_theindiancoder/Binomialdistribution.py
distributions_theindiancoder/Gaussiandistribution.py
distributions_theindiancoder/Generaldistribution.py
distributions_theindiancoder/__init__.py
distributions_theindiancoder.egg-info/PKG-INFO
distributions_theindiancoder.egg-info/SOURCES.txt
distributions_theindiancoder.egg-info/dependency_links.txt
distributions_theindiancoder.egg-info/top_level.txt
distributions_theindiancoder.egg-info/zip-safe