Metadata-Version: 1.0
Name: distributions-theindiancoder
Version: 0.1
Summary: Gaussian and Binomial distributions
Home-page: UNKNOWN
Author: theindiancoder
Author-email: UNKNOWN
License: UNKNOWN
Platform: UNKNOWN
